[
  {"name": "Coca cola", "category": "Boissons", "price": 2, "image": "img/Coca cola.jpg"},
  {"name": "Coca zéro", "category": "Boissons", "price": 2, "image": "img/Coca zéro.jpg"},
  {"name": "Fanta", "category": "Boissons", "price": 2, "image": "img/Fanta.jpg"},
  {"name": "Oasis", "category": "Boissons", "price": 2, "image": "img/Oasis.jpg"},
  {"name": "Ice Tea", "category": "Boissons", "price": 2, "image": "img/Ice Tea.jpg"},
  {"name": "Cristaline", "category": "Boissons", "price": 1.5, "image": "img/Cristaline.jpg"},
  {"name": "Perrier", "category": "Boissons", "price": 2, "image": "img/Perrier.jpg"},
  {"name": "Cristaline pétillante", "category": "Boissons", "price": 2, "image": "img/Cristaline pétillante.jpg"},
  {"name": "Café", "category": "Chaud", "price": 1.5, "image": "img/Café.jpg"},
  {"name": "Thé", "category": "Chaud", "price": 1.5, "image": "img/Thé.jpg"},
  {"name": "Chocolat chaud", "category": "Chaud", "price": 1.5, "image": "img/Chocolat chaud.jpg"},
  {"name": "Sandwich saucisse", "category": "Salé", "price": 4, "image": "img/Sandwich saucisse.jpg"},
  {"name": "Sandwich merguez", "category": "Salé", "price": 4, "image": "img/Sandwich merguez.jpg"},
  {"name": "Sandwich camembert", "category": "Salé", "price": 4, "image": "img/Sandwich camembert.jpg"},
  {"name": "Part de pizza fromage", "category": "Salé", "price": 4, "image": "img/Part de pizza fromage.jpg"},
  {"name": "Panini jambon", "category": "Salé", "price": 5, "image": "img/Panini jambon.jpg"},
  {"name": "Panini Nutella", "category": "Sucré", "price": 5, "image": "img/Panini Nutella.jpg"},
  {"name": "Crêpe sucre", "category": "Sucré", "price": 2, "image": "img/Crêpe sucre.jpg"},
  {"name": "Crêpe Nutella", "category": "Sucré", "price": 3, "image": "img/Crêpe Nutella.jpg"},
  {"name": "Mars", "category": "Friandises", "price": 2, "image": "img/Mars.jpg"},
  {"name": "Twix", "category": "Friandises", "price": 2, "image": "img/Twix.jpg"},
  {"name": "Lion", "category": "Friandises", "price": 2, "image": "img/Lion.jpg"},
  {"name": "Bounty", "category": "Friandises", "price": 2, "image": "img/Bounty.jpg"},
  {"name": "Kinder bueno", "category": "Friandises", "price": 2, "image": "img/Kinder bueno.jpg"},
  {"name": "Kitkat", "category": "Friandises", "price": 2, "image": "img/Kitkat.jpg"},
  {"name": "Snickers", "category": "Friandises", "price": 2, "image": "img/Snickers.jpg"},
  {"name": "Croissant", "category": "Petit dej", "price": 2.5, "image": "img/Croissant.jpg"},
  {"name": "Pain au chocolat", "category": "Petit dej", "price": 2.5, "image": "img/Pain au chocolat.jpg"},
  {"name": "Formule petit-déjeuner (1 viennoiserie + 1 boisson chaude)", "category": "Petit dej", "price": 3, "image": "img/Formule petit dej.jpg"}
]
